clustermil/__init__.py
clustermil/__version__.py
clustermil/classification.py
clustermil-0.2.0.dist-info/LICENSE
clustermil-0.2.0.dist-info/WHEEL
clustermil-0.2.0.dist-info/METADATA
clustermil-0.2.0.dist-info/RECORD
