Metadata-Version: 2.1
Name: clustermil
Version: 0.2.0
Summary: clustermil - clustering based multiple instance learning
Home-page: https://github.com/inoueakimitsu/clustermil
License: MIT
Keywords: machine learning,multiple instance learning,scikit-learn
Author: Inoue Akimitsu
Author-email: inoue.akimitsu@gmail.com
Requires-Python: >=3.8,<4.0
Classifier: Development Status :: 4 - Beta
Classifier: Intended Audience :: Developers
Classifier: License :: OSI Approved :: MIT License
Classifier: Programming Language :: Python :: 3
Classifier: Programming Language :: Python :: 3.10
Classifier: Programming Language :: Python :: 3.8
Classifier: Programming Language :: Python :: 3.9
Requires-Dist: PuLP (>=2.6.0,<3.0.0)
Requires-Dist: numpy (>=1.23.1,<2.0.0)
Requires-Dist: pandas (>=1.4.3,<2.0.0)
Requires-Dist: scikit-learn (>=1.1.1,<2.0.0)
Project-URL: Repository, https://github.com/inoueakimitsu/clustermil
